LICENSE
MANIFEST.in
README
logo.png
requirements.txt
setup.py
btp/__init__.py
btp/run.py
btp/util/__init__.py
btp/util/fetcher.py
btp/util/postman.py
btp/util/req.py
btp/util/trackers.py
btrackers_postman.egg-info/PKG-INFO
btrackers_postman.egg-info/SOURCES.txt
btrackers_postman.egg-info/dependency_links.txt
btrackers_postman.egg-info/entry_points.txt
btrackers_postman.egg-info/requires.txt
btrackers_postman.egg-info/top_level.txt